chemsy/__init__.py
chemsy/explore.py
chemsy/help.py
chemsy/visual.py
chemsy/predict/__init__.py
chemsy/predict/methods.py
chemsy/prep/__init__.py
chemsy/prep/methods.py
Chemsy-1.1.dist-info/LICENSE
Chemsy-1.1.dist-info/METADATA
Chemsy-1.1.dist-info/WHEEL
Chemsy-1.1.dist-info/top_level.txt
Chemsy-1.1.dist-info/RECORD
