Metadata-Version: 2.1
Name: Chemsy
Version: 1.1
Summary: Chemsy: A Minimalistic Automated Framework for Chemometrics and Machine Learning
Author: Sin Yong Teng
Author-email: tsyet12@gmail.com
License: BSD 2-Clause
Keywords: Machine Learning,Chemometrics,Process Analytical Technology,Spectroscopy
Classifier: Development Status :: 4 - Beta
Classifier: Intended Audience :: Developers
Classifier: Topic :: Software Development :: Build Tools
Classifier: License :: OSI Approved :: BSD License
Classifier: Programming Language :: Python :: 3
Classifier: Programming Language :: Python :: 3.4
Classifier: Programming Language :: Python :: 3.5
Classifier: Programming Language :: Python :: 3.6
License-File: LICENSE
Requires-Dist: numpy
Requires-Dist: matplotlib
Requires-Dist: scikit-learn
Requires-Dist: BaselineRemoval
Requires-Dist: scipy
Requires-Dist: tqdm
